<?xml version='1.0' encoding='utf-8'?>
<data>
  <row>
    <pope>ALEXANDER III.</pope>
    <date>1162 Dec. 8.</date>
    <place>Turoni</place>
    <number>10789 (7239)</number>
    <text>Ludovico, Francorum regi, significat, se, quos misisset, Barbadorum eiusque comitem militem benigne recepisse, iisque, ut antea iam Mauricio, episcopo Parisiensi, mandasse, ut de celebrando concilio ad eum referrent. Duchesne Hist. Fr. SS. IV. 621, Bouquet Rec. XV. 787, Mansi XXI. 1017, Migne 200 p. 183.</text>
    <incipit>„Dilectos filios nostros“.</incipit>
  </row>
</data>
