<?xml version='1.0' encoding='utf-8'?>
<data>
  <row>
    <pope>ALEXANDER III.</pope>
    <date>1177 „ 24.</date>
    <place>Rivo alto</place>
    <number>12890</number>
    <text>Ecclesiae S. Salvatoris de Rivalto controversiam cum Slavo de Mestre, ab epi- scopo Tarvisino ad sedem apostolicam appellante, ita se diiudicasse testatur, ut hic molendina, in detrimentum molendinorum S. Salvatoris constructa, destruere debeat. Pflugk-Harttung Acta III. 259. — „Conquerentibus vobis“.</text>
  </row>
</data>
