<?xml version='1.0' encoding='utf-8'?>
<data>
  <row>
    <pope>ALEXANDER III.</pope>
    <date>1177 „ 3.</date>
    <place>Rivo alto</place>
    <number>12912 (8524)</number>
    <text>Choro ecclesiae Salzburgensis, praelatis ecclesiarum et ministerialibus praescriptae ecclesiae entra montana constitutis significat, in Adalberti locum, qui archiepiscopatu sua sponte abdicasset, ab episcopis (Romano) Gurcensi et (Theobaldo) Passaviensi, praelatisque Salzburgensibus, qui affuerint, Chunradum Moguntinum elec- tum esse; cui ut, sacramento quod Adalberto praestitissent soluti, obtemperent, hortatur. Chron. Magni presb. 1177 in MG. SS. XVII. 505, Hund I. 72, Mansi XXII. 191, Migne 200 p. 1141. — „Venerabilis frater noster“.</text>
  </row>
</data>
