<?xml version='1.0' encoding='utf-8'?>
<data>
  <row>
    <pope>ALEXANDER III.</pope>
    <date>1166— 1179 Marnt. 31.</date>
    <place>Laterani</place>
    <number>13196</number>
    <text>(Alberto) episcopo Frisingensi petente, „ecclesiam S. Iohannis baptistae, aliasque dotes, quas altaribus in consecratione in decimis sive bonis aliis contulerit, eisdem altaribus confirmat“. Oberbayerisches Archiv XII. 223, Pflugk-Harttung Acta III. 267.</text>
    <incipit>„Cum peticiones singulorum“.</incipit>
  </row>
</data>
