<?xml version='1.0' encoding='utf-8'?>
<data>
  <row>
    <pope>ALEXANDER III.</pope>
    <date>1179 „ 6.</date>
    <place>Laterani</place>
    <number>13369</number>
    <text>(Willelmo) archiepiscopo Remensi, presbytero cardinali (tit. S. Sabinae), aposto- licae sedis legato, eiusque suffraganeis aliisque viris ecclesiasticis mandat, ne a fra- tribus Montis-dei et Vallis S. Petri vel ab aliis ordinis Cartusiensis (1) monachis decimas de laboribus vel de nutrimentis animalium exigi patiantur. Copia s. XIV. (?) in tabul. nat. Paris. L. 231. n. 65. — „Audivimus et audientes“.</text>
  </row>
</data>
