<?xml version='1.0' encoding='utf-8'?>
<data>
  <row>
    <pope>ALEXANDER III.</pope>
    <date>1180 Febr. 25.</date>
    <place>Velletri</place>
    <number>13622 (8785)</number>
    <text>Archiepiscopis et episcopis Sardiniae praecipit, ne contra concilii nuper celebrati decreta ecclesiarum monasterii Casinensis privilegia invadant. Gattulae Hist. Cas. p. 430, Tosti St. di Montec. II. 208, Hist. Patr. Mon. X. 222, Migne 200 p. 1267.</text>
    <incipit>„Audivimus et audientes“.</incipit>
  </row>
</data>
