<?xml version='1.0' encoding='utf-8'?>
<data>
  <row>
    <pope>ALEXANDER III.</pope>
    <date>1181 Mart. 23.</date>
    <place>Tusenlani</place>
    <number>14380</number>
    <text>H(ugoni) episcopo Dunelmensi et abbati S. Albani mandat, curent, ne (Richardus) archiepiscopus Cantuariensis et eius officiales, lite super privilegiis S. Augustini pen- dente (v. supra 14365), de possessionibus monasterii, vel hominibus, clericis et ec- clesiis se aliquatenus intromittant. Hist. mon. S. Aug. Cant. p. 441. — „Cum super quaestionem“.</text>
  </row>
</data>
