<?xml version='1.0' encoding='utf-8'?>
<data>
  <row>
    <pope>ALEXANDER III.</pope>
    <date>1166—1167 „„„„</date>
    <place>Laterani</place>
    <number>11322 (7562)</number>
    <text>Abbati et fratribus Cluniacensibus significat, electionem Raimundi, abbatis S. Benedicti Padilironensis, „propter itineris difficultatem et schismaticorum saevien- tium feritatem“ ab Ildebrando. presbytero card. basilicae XII apostolorum, aliisque confirmatam, a sese roboratam esse, salvis iuribus Cluniacensibus. Bull. Clun. p. 72, Migne 200 p. 435. — „Venerabilis frater noster“.</text>
  </row>
</data>
