<?xml version='1.0' encoding='utf-8'?>
<data><row><pope /><date /><place /><number /><incipit>„Perlatum est ad“.</incipit><abstract>Henrico, archiepiscopo Remensi, mandat, compellat canonicos Arienses, ut monasterio S. Vedasti, quod Philippus comes Flandrensis abstulerit, caput b. Iacobi restituant. Guimann Cart. de S.-Vaast d'Arras p. 136, Revue des soc. sav. V. sér. VII. 544: „IIII. Id. Iul.“, Martene Coll. II. 811, Bouquet Rec. XV. 861, Migne 200 p. 544: „VII. kal. Iun.“.</abstract><notBefore>1168-01-12</notBefore><notAfter>1169-12-12</notAfter></row></data>