<?xml version='1.0' encoding='utf-8'?>
<data><row><pope>ALEXANDER III.</pope><date>1171— 1172 Mart. 4.</date><place>„uestani</place><number>11996 (8042)</number><incipit>„Dilectos filios nostros“.</incipit><abstract>Henrico, archiepiscopo Remensi, nunciat, S. magistrum de D. fratrem militiae templi, nuncium eius, a sese benigne receptum esse. Hortatur, ut „ex quo (Petrus) episcopus Cameracensis se in conspectu eius humiliaverit, et ab eo misericordiam et veniam expetierit, ei rancorem et indignationem remittat“. Martene Coll. II. 892, Bouquet Rec. XV. 902, Migne 200 p. 785.</abstract><notBefore>1171-01-04</notBefore><notAfter>1172-12-04</notAfter></row></data>