<?xml version='1.0' encoding='utf-8'?>
<data><row><pope>ALEXANDER III.</pope><date>1177 Iun. 4.</date><place>Venetiis in Rivo alto</place><number>12864</number><incipit>„Ex litteris vestris“.</incipit><abstract>O(berti) episcopi et canonicorum Dertonensium confirmat statutum, ut „ultra sedecim numerus canonicorum non extendatur“ utque, qui studio vacaverint litterarum, medietatem integrae portionis frumenti et siliginis habeant et nihil amplius exigant. Pflugk-Harttung Acta III. 257.</abstract><notBefore>1177-06-04</notBefore><notAfter>1177-06-04</notAfter></row></data>