<?xml version='1.0' encoding='utf-8'?>
<data><row><pope>ALEXANDER III.</pope><date>1178</date><place> Tusculani</place><number>13103</number><incipit>„Receptis vestre devotionis“.</incipit><abstract>(Martino) episcopo, consulibus et populo Nepesinis significat, prohibiturum se esse, quominus pro auxilio Viterbiensibus praestito a (Conrado) filio marchionis (Willelmi de Monteferrato) molestiis afficiantur. Loewenfeld Epistolae p. 161. Cf. ea quae exposui in Forsch. z. d. Gesch. XXV. 459. 460.</abstract><notBefore>1178-01-01</notBefore><notAfter>1178-12-31</notAfter></row></data>