<?xml version='1.0' encoding='utf-8'?>
<data><row><pope>ALEXANDER III.</pope><date>1180 c. Mai. Iun.</date><place> Velletri</place><number>13663</number><incipit>„Audientes a pluribus“</incipit><abstract>(Michaeli) decano et capitulo Meldensi praecipit, moneant (Simonem) episcopum Meldensem, ut H(erveo) canonico integram Hugonis de Oratorio nuper defuncti praebendam assignet, vel dimidiam eius tandem integret. De negotio (Matthaeo) Trecensi episcopo dato addit. Loewenteld Epistolae p. 192.</abstract></row></data>