<?xml version='1.0' encoding='utf-8'?>
<data><row><pope>ALEXANDER III.</pope><date>1159 — 1181</date><place> </place><number>13949 (9012)</number><incipit>„Ad haec cum contingat“.</incipit><abstract>Episcopo Herefordensi scribit, „in ecclesiasticis personis et negotiis rigorem et districtionem iuris non esse requirendum“. App. conc. Lat. III. 1, Coll. Lips. XL. 1. Coll. Cass. XLVI. 1, Coll. Bamb. XXXVII. 1, Comp. I. L. 2. t. 10. c. 1, Decr. Greg. L. II. t. 14. c. 1.</abstract><notBefore>1159-01-01</notBefore><notAfter>1181-12-31</notAfter></row></data>