<?xml version='1.0' encoding='utf-8'?>
<data><row><pope>ALEXANDER III.</pope><date>1164— 1165 lan. 26.</date><place>Senonis</place><number>11106</number><incipit>„Ex relatione fratrum“.</incipit><abstract>G(uillelmum) episcopum Hlerdensem reprehendit, quod M. quendam ex fratribus hospitalis Iherosolimitani in eorum coemeterio sepeliri prohibuerit eisque ecclesiam de Rateria abstulerit. Praecipit, ut ecclesiam restituat mortuumque sepeliri sinat. Villanueva Viage literar. XVI. 273.</abstract><notBefore>1164-01-26</notBefore><notAfter>1165-12-26</notAfter></row></data>