<?xml version='1.0' encoding='utf-8'?>
<data><row><pope>ALEXANDER III.</pope><date>1164—1165 Mart 3.</date><place>Senonis</place><number>11124</number><incipit>„Iustis petentium desideriis“.</incipit><abstract>Capitulo S. Audomari asserit ea, „quae b. m. A. praepositus de propriis facultatibus ad instaurationem duarum praebendarum“ ei contulerit. Ex autographo in tabul. capit. Audomarensi dedit Arthurus Giry Parisiensis.</abstract><notBefore>1164-03-03</notBefore><notAfter>1165-03-03</notAfter></row></data>