<?xml version='1.0' encoding='utf-8'?>
<data>
  <row>
    <pope>ALEXANDER III.</pope>
    <date>1159— 1181</date>
    <place> </place>
    <number>13851 (8918)</number>
    <text>Episcopis quibusdam mandat, interdicant archidiaconis, decanis et pres- byteris, „ne in famulos vel mercenarios fratrum Cisterciensium, pro eo, quod quibus- dam diebus laborent, quos alii solemnes habeant, vel excommunicationis vel interdicti sententiam ferant“. Comp. II. L. 2. t. 5. c. 1, Mansi XXI. 1094. — „Significantibus nobis“.</text>
  </row>
</data>
