<?xml version='1.0' encoding='utf-8'?>
<data>
  <row>
    <pope>ALEXANDER III.</pope>
    <date>1159— 1181</date>
    <place> </place>
    <number>14124 (9183)</number>
    <text>Episcopo Verulano scribit: „Octavianus avus Octaviani de Tracterio quan- dam feminam carnaliter cognovit, ex qua filium procreavit, et postmodum virum accipiens, filium generavit, cui Octavianus praedicti Octaviani nepos filiam suam tradere disposuit uxorem“. Mandat, ut matrimonium prohibeat. Comp. I. L. 4. t. 15. c. 2. — „Quia nobis significatum“.</text>
  </row>
</data>
