<?xml version='1.0' encoding='utf-8'?>
<data><row><pope>ALEXANDER III.</pope><date>1171— 1173 Sept. 17.</date><place>raaenlani</place><number>12120 (8150)</number><incipit>„Omnes, qui pie“.</incipit><abstract>Universos Dei fideles per Daciam constitutos hortatur, ut Fulconis, Estonum episcopi „ad convertendam gentem illam totis viribus elaborantis“, inopiam sublevent. Sirmondi Opp. III. 865, Bunge Livl. Urkundenb. I. 7, Mansi XXI. 936, Migne 200 p. 862.</abstract><notBefore>1171-09-17</notBefore><notAfter>1173-09-17</notAfter></row></data>