<?xml version='1.0' encoding='utf-8'?>
<data><row><pope>ALEXANDER III.</pope><date>1172 Pebr. 17.</date><place>ruenteni.</place><number>12140</number><incipit>„Religiosam vitam“.</incipit><abstract>Monasterii Vadi Ulmi tutelam suscipit ac disciplinam, possessiones, privilegia confirmat. Ex chartul. S. Evurtii p. 503 ms. lat. 10089 in bibl. nat. Paris. misit Delisle; Coll. Baluze t. 78. f. 728is in eadem bibl.</abstract><notBefore>1172-02-17</notBefore><notAfter>1172-02-17</notAfter></row></data>