<?xml version='1.0' encoding='utf-8'?>
<data><row><pope>ALEXANDER III.</pope><date>1159—1181</date><place> </place><number>14136 (9201)</number><incipit>„Consuluit nos tua“.</incipit><abstract>Episcopo Wigorniensi respondet de Wilielmo, „qui licet fidem dedisset, quod mulierem quandam duceret in uxorem, ipse sibi aliam copulare praesumpserit“. App. conc. Lat. VI. 2, Coll. Lips. LIX. 2, Coll. Cass. LVIII. 3, Coll. Bamb. LI. 3, Comp. I. L. 4. t. 1. c. 3.</abstract><notBefore>1159-01-01</notBefore><notAfter>1181-12-31</notAfter></row></data>