<?xml version='1.0' encoding='utf-8'?>
<data><row><pope /><date /><place /><number /><incipit>„Illud praetereundum" ,,Illud vero praetereundum".</incipit><abstract>Episcopo Wintoniensi sic scribit; ,,si laicus, episcopo inconsulto, ecclesiam non vacantem concedit alicui religiosae domui, postea, cum vo.caverit, ad praesentationem eiusdem laici aliquis clericus ibi fuerit per episcopum institutus, prior concessio secundam institutionem 11011 potest impedire". (Fartasse pars mit op. 1415ti.) App. conc. Lat. XV. 6, Coll. Lips. LJI. 5, Coll. Bamb. XL V. 4, Coll. Cass. LIII. 5, Comp. I. L. 3. t. 33. c. 11, Decr. Greg. L. III. t. 38. c. 8.</abstract></row></data>